biocontext_kb/__init__.py
biocontext_kb/app.py
biocontext_kb/logging.py
biocontext_kb/main.py
biocontext_kb/py.typed
biocontext_kb/core/__init__.py
biocontext_kb/core/_server.py
biocontext_kb/core/alphafold/__init__.py
biocontext_kb/core/alphafold/_get_alphafold_info_by_protein_symbol.py
biocontext_kb/core/alphafold/_get_alphafold_info_by_uniprot_id.py
biocontext_kb/core/antibodyregistry/__init__.py
biocontext_kb/core/antibodyregistry/_get_antibody_information.py
biocontext_kb/core/antibodyregistry/_get_antibody_list.py
biocontext_kb/core/biorxiv/__init__.py
biocontext_kb/core/biorxiv/_get_preprint_details.py
biocontext_kb/core/biorxiv/_get_recent_biorxiv_preprints.py
biocontext_kb/core/clinicaltrials/__init__.py
biocontext_kb/core/clinicaltrials/_get_recruiting_studies_by_location.py
biocontext_kb/core/clinicaltrials/_get_studies_by_condition.py
biocontext_kb/core/clinicaltrials/_get_studies_by_intervention.py
biocontext_kb/core/clinicaltrials/_get_study_details.py
biocontext_kb/core/clinicaltrials/_search_studies.py
biocontext_kb/core/ensembl/__init__.py
biocontext_kb/core/ensembl/_get_ensembl_id_from_gene_symbol.py
biocontext_kb/core/europepmc/__init__.py
biocontext_kb/core/europepmc/_get_europepmc_articles.py
biocontext_kb/core/europepmc/_get_europepmc_fulltext.py
biocontext_kb/core/grants/__init__.py
biocontext_kb/core/grants/_search_grants_gov.py
biocontext_kb/core/interpro/__init__.py
biocontext_kb/core/interpro/_get_interpro_entry.py
biocontext_kb/core/interpro/_get_protein_domains.py
biocontext_kb/core/interpro/_search_interpro_entries.py
biocontext_kb/core/kegg/__init__.py
biocontext_kb/core/kegg/_execute_kegg_query.py
biocontext_kb/core/kegg/_get_kegg_id_by_gene_symbol.py
biocontext_kb/core/kegg/_query_kegg.py
biocontext_kb/core/ols/__init__.py
biocontext_kb/core/ols/_get_available_ontologies.py
biocontext_kb/core/ols/_get_cell_ontology_terms.py
biocontext_kb/core/ols/_get_chebi_terms_by_chemical.py
biocontext_kb/core/ols/_get_efo_id_by_disease_name.py
biocontext_kb_fastmcp-0.2.2.dist-info/METADATA
biocontext_kb_fastmcp-0.2.2.dist-info/WHEEL
biocontext_kb_fastmcp-0.2.2.dist-info/entry_points.txt
biocontext_kb_fastmcp-0.2.2.dist-info/licenses/LICENSE
biocontext_kb_fastmcp-0.2.2.dist-info/RECORD
