Metadata-Version: 2.4
Name: biocontext_kb-fastmcp
Version: 0.2.2
Summary: A knowledgebase MCP server for biomedical research, part of the BioContextAI project.
Project-URL: Homepage, https://github.com/fastmcp-me/knowledgebase-mcp#readme
Project-URL: Repository, https://github.com/fastmcp-me/knowledgebase-mcp.git
Project-URL: Issues, https://github.com/fastmcp-me/knowledgebase-mcp/issues
License-File: LICENSE
Classifier: Development Status :: 4 - Beta
Classifier: Intended Audience :: Developers
Classifier: Intended Audience :: Healthcare Industry
Classifier: Intended Audience :: Science/Research
Classifier: License :: OSI Approved :: Apache Software License
Classifier: Natural Language :: English
Classifier: Operating System :: OS Independent
Classifier: Programming Language :: Python :: 3
Classifier: Programming Language :: Python :: 3.12
Requires-Python: >=3.12
Requires-Dist: asyncio<4,>=3.4.3
Requires-Dist: dotenv<1,>=0.9.9
Requires-Dist: fastmcp==2.13.1
Requires-Dist: gql<4,>=3.5.3
Requires-Dist: gunicorn<24,>=23.0.0
Requires-Dist: httpx>=0.28.1
Requires-Dist: numpy<3,>=2.2.5
Requires-Dist: pandas-stubs>=2.2.3.250308
Requires-Dist: pandas<3,>=2.2.3
Requires-Dist: pillow>=11.2.1
Requires-Dist: pyyaml>=6.0.2
Requires-Dist: requests-toolbelt>=1.0.0
Requires-Dist: requests<3,>=2.32.3
Requires-Dist: scholarly>=1.7.11
Requires-Dist: types-pyyaml>=6.0.12.20250402
Requires-Dist: types-requests>=2.32.0.20250328
Requires-Dist: uvicorn-worker>=0.3.0
